Metadata-Version: 2.1
Name: matrix-henryj
Version: 1.0.0
Summary: A package implementing matrices
Home-page: https://github.com/grudat20/henryj-ovn7
Author: Henry
Author-email: henryj@kth.se
License: UNKNOWN
Platform: UNKNOWN
Classifier: Programming Language :: Python :: 3
Classifier: License :: OSI Approved :: BSD License
Classifier: Operating System :: OS Independent
Requires-Python: >=3.6
